sqldf/__init__.py
sqldf/sqldf.py
sqldf-0.4.2.dist-info/LICENSE
sqldf-0.4.2.dist-info/METADATA
sqldf-0.4.2.dist-info/WHEEL
sqldf-0.4.2.dist-info/top_level.txt
sqldf-0.4.2.dist-info/RECORD
