Metadata-Version: 2.1
Name: sqldf
Version: 0.4.2
Summary: A simple way to run SQL queries (SQLite3) on pandas.Dataframe objects.
Home-page: https://github.com/christophelebrun/sqldf
Author: Christophe Lebrun
Author-email: lebr1.christophe@gmail.com
License: MIT
Platform: UNKNOWN
